{
  "$schema": "https://schema.management.azure.com/schemas/2019-04-01/deploymentTemplate.json#",
  "contentVersion": "1.0.0.0",
  "parameters": {
    "location": {
      "type": "string",
      "defaultValue": "[resourceGroup().location]"
    },
    "vnetName": {
      "type": "string",
      "metadata": {
        "description": "The name for the virtual network"
      }
    },
    "addressPrefix": {
      "type": "string",
      "defaultValue": "10.0.0.0/16",
      "metadata": {
        "description": "The address space for the virtual network"
      }
    },
    "subnetName": {
      "type": "string",
      "defaultValue": "Default",
      "metadata": {
        "description": "The name for the subnet"
      }
    },
    "subnetPrefix": {
      "type": "string",
      "defaultValue": "10.0.0.0/24",
      "metadata": {
        "description": "The address space for the subnet"
      }
    }
  },
  "variables": {},
  "resources": [
    {
      "apiVersion": "2019-09-01",
      "type": "Microsoft.Network/virtualNetworks",
      "name": "[parameters('vnetName')]",
      "location": "[parameters('location')]",
      "properties": {
        "addressSpace": {
          "addressPrefixes": [
            "[parameters('addressPrefix')]"
          ]
        },
        "subnets": [
          {
            "name": "[parameters('subnetName')]",
            "properties": {
              "addressPrefix": "[parameters('subnetPrefix')]"
            }
          }
        ]
      }
    }
  ],
  "outputs": {}
}